Lab 1/four bit adder full stimulus creater/four_bit_adder.v
/*
 * Generated by Digital. Don't modify this file!
 * Any changes will be lost if this file is regenerated.
 */

module full_adder (
  input a,
  input b,
  input cin,
  output sum,
  output cout
);
  assign sum = (a ^ b ^ cin);
  assign cout = ((b & cin) | (cin & a) | (b & a));
endmodule

module four_bit_adder (
  input [3:0] a,
  input [3:0] b,
  input cin,
  output [3:0] y,
  output overfl,
  output cout
);
  wire s0;
  wire s1;
  wire s2;
  wire s3;
  wire s4;
  wire s5;
  wire s6;
  wire s7;
  wire s8;
  wire s9;
  wire s10;
  wire s11;
  wire s12;
  wire s13;
  wire s14;
  wire cout_temp;
  assign s0 = a[0];
  assign s1 = a[1];
  assign s2 = a[2];
  assign s3 = a[3];
  assign s4 = b[0];
  assign s5 = b[1];
  assign s6 = b[2];
  assign s7 = b[3];
  full_adder full_adder_i0 (
    .a( s0 ),
    .b( s4 ),
    .cin( cin ),
    .sum( s8 ),
    .cout( s9 )
  );
  full_adder full_adder_i1 (
    .a( s1 ),
    .b( s5 ),
    .cin( s9 ),
    .sum( s10 ),
    .cout( s11 )
  );
  full_adder full_adder_i2 (
    .a( s2 ),
    .b( s6 ),
    .cin( s11 ),
    .sum( s12 ),
    .cout( s13 )
  );
  full_adder full_adder_i3 (
    .a( s3 ),
    .b( s7 ),
    .cin( s13 ),
    .sum( s14 ),
    .cout( cout_temp )
  );
  assign y[0] = s8;
  assign y[1] = s10;
  assign y[2] = s12;
  assign y[3] = s14;
  assign overfl = (s13 ^ cout_temp);
  assign cout = cout_temp;
endmodule

Lab 1/four bit adder full stimulus creater/four_bit_adder_top.v
// Test module for lab 0
`timescale 1ns/1ns          // set a realistic time scale for the simulation

module full_adder_top();

reg [19:0] resp_data[0:511]; // stimulus and response. This array is 16 rows and 20 columns
reg [3:0] in_a;             // the a input to the circuit
reg [3:0] in_b;             // the b input to the circuit
reg cin;                    // the cin input to the circuit
wire [3:0] sum;             // the sum output
wire cout;                  // the cout output
wire overfl;                // the overflow output
reg [5:0] exp_out;          // the expected output

integer index;              // index into the input/output arrays

initial                     // read the arrays
begin
   $readmemh("stimulus_output.txt",resp_data);  // read the inputs and expected respnses
end

initial    // all initial blocks run at start up...
begin
   for ( index = 0 ; index < 512 ; index = index+1 )  // for each of the rows in the table
   begin
      {cin,in_a,in_b} = resp_data[index][8:0];       // get the next inputs.

      exp_out = resp_data[index][17:12];             // get the expected outputs.

      #1;                                    // wait for propagation
      if ( {overfl,cout,sum} != exp_out )     // did we get what was expected?
         $display("Output mismatch for entry ",index," expected ",
                  exp_out," but got overfl, cout, and sum ",overfl,cout,sum);
   end
end

// this instantiates your design
four_bit_adder four_bit_adder(.a(in_a),.b(in_b),.cin(cin), .y(sum),.cout(cout),.overfl(overfl)); 

// dump the output to a VCD file so the waveform viewer can create the display
initial
begin
   $dumpfile("four_bit_adder_waves.vcd"); // the name of the output file containing the waves
   $dumpvars(0,four_bit_adder);           // 0 dumps all signals from full_adder down
end

endmodule

Lab 1/four bit adder full stimulus creater/four_bit_adder_waves.vcd
$date
	Mon Jan 26 20:37:53 2026
$end
$version
	Icarus Verilog
$end
$timescale
	1ns
$end
$scope module full_adder_top $end
$scope module four_bit_adder $end
$var wire 4 ! a [3:0] $end
$var wire 4 " b [3:0] $end
$var wire 1 # cin $end
$var wire 1 $ cout $end
$var wire 1 % overfl $end
$var wire 4 & y [3:0] $end
$var wire 1 ' s9 $end
$var wire 1 ( s8 $end
$var wire 1 ) s7 $end
$var wire 1 * s6 $end
$var wire 1 + s5 $end
$var wire 1 , s4 $end
$var wire 1 - s3 $end
$var wire 1 . s2 $end
$var wire 1 / s14 $end
$var wire 1 0 s13 $end
$var wire 1 1 s12 $end
$var wire 1 2 s11 $end
$var wire 1 3 s10 $end
$var wire 1 4 s1 $end
$var wire 1 5 s0 $end
$var wire 1 6 cout_temp $end
$scope module full_adder_i0 $end
$var wire 1 5 a $end
$var wire 1 , b $end
$var wire 1 # cin $end
$var wire 1 ' cout $end
$var wire 1 ( sum $end
$upscope $end
$scope module full_adder_i1 $end
$var wire 1 4 a $end
$var wire 1 + b $end
$var wire 1 ' cin $end
$var wire 1 2 cout $end
$var wire 1 3 sum $end
$upscope $end
$scope module full_adder_i2 $end
$var wire 1 . a $end
$var wire 1 * b $end
$var wire 1 2 cin $end
$var wire 1 0 cout $end
$var wire 1 1 sum $end
$upscope $end
$scope module full_adder_i3 $end
$var wire 1 - a $end
$var wire 1 ) b $end
$var wire 1 0 cin $end
$var wire 1 6 cout $end
$var wire 1 / sum $end
$upscope $end
$upscope $end
$upscope $end
$enddefinitions $end
$comment Show the parameter values. $end
$dumpall
$end
#0
$dumpvars
06
05
04
03
02
01
00
0/
0.
0-
0,
0+
0*
0)
0(
0'
b0 &
0%
0$
0#
b0 "
b0 !
$end
#1
b1 &
1(
15
b1 !
#2
0(
b10 &
13
05
14
b10 !
#3
b11 &
1(
15
b11 !
#4
0(
03
b100 &
11
05
04
1.
b100 !
#5
b101 &
1(
15
b101 !
#6
0(
b110 &
13
05
14
b110 !
#7
b111 &
1(
15
b111 !
#8
0(
03
01
b1000 &
1/
05
04
0.
1-
b1000 !
#9
b1001 &
1(
15
b1001 !
#10
0(
b1010 &
13
05
14
b1010 !
#11
b1011 &
1(
15
b1011 !
#12
0(
03
b1100 &
11
05
04
1.
b1100 !
#13
b1101 &
1(
15
b1101 !
#14
0(
b1110 &
13
05
14
b1110 !
#15
b1111 &
1(
15
b1111 !
#16
03
01
b1 &
0/
05
04
0.
0-
1,
b0 !
b1 "
#17
13
b10 &
0(
1'
15
b1 !
#18
01
02
1(
0'
b11 &
13
05
14
b10 !
#19
11
12
03
b100 &
0(
1'
15
b11 !
#20
0/
0%
02
00
1(
0'
03
b101 &
11
05
04
1.
b100 !
#21
13
b110 &
0(
1'
15
b101 !
#22
0/
0%
00
11
02
1(
0'
b111 &
13
05
14
b110 !
#23
1/
1%
10
01
12
03
b1000 &
0(
1'
15
b111 !
#24
0%
02
00
0$
06
1(
0'
03
01
b1001 &
1/
05
04
0.
1-
b1000 !
#25
13
b1010 &
0(
1'
15
b1001 !
#26
01
02
1(
0'
b1011 &
13
05
14
b1010 !
#27
11
12
03
b1100 &
0(
1'
15
b1011 !
#28
0$
06
1/
0%
02
00
1(
0'
03
b1101 &
11
05
04
1.
b1100 !
#29
13
b1110 &
0(
1'
15
b1101 !
#30
0$
06
1/
0%
00
11
02
1(
0'
b1111 &
13
05
14
b1110 !
#31
1$
16
0/
0%
10
01
12
03
b0 &
0(
1'
15
b1111 !
#32
02
00
0$
06
13
01
b10 &
0/
0'
05
04
0.
0-
0,
1+
b0 !
b10 "
#33
b11 &
1(
15
b1 !
#34
11
0(
b100 &
03
12
05
14
b10 !
#35
b101 &
1(
15
b11 !
#36
0/
0%
00
0(
13
02
b110 &
11
05
04
1.
b100 !
#37
b111 &
1(
15
b101 !
#38
1/
1%
10
01
0(
b1000 &
03
12
05
14
b110 !
#39
b1001 &
1(
15
b111 !
#40
0%
00
0$
06
0(
13
02
01
b1010 &
1/
05
04
0.
1-
b1000 !
#41
b1011 &
1(
15
b1001 !
#42
11
0(
b1100 &
03
12
05
14
b1010 !
#43
b1101 &
1(
15
b1011 !
#44
0$
06
1/
0%
00
0(
13
02
b1110 &
11
05
04
1.
b1100 !
#45
b1111 &
1(
15
b1101 !
#46
1$
16
0/
0%
10
01
0(
b0 &
03
12
05
14
b1110 !
#47
b1 &
1(
15
b1111 !
#48
00
0$
06
13
02
01
b11 &
0/
05
04
0.
0-
1,
b0 !
b11 "
#49
11
12
03
b100 &
0(
1'
15
b1 !
#50
1(
0'
b101 &
03
05
14
b10 !
#51
13
b110 &
0(
1'
15
b11 !
#52
02
0/
0%
00
1(
0'
13
b111 &
11
05
04
1.
b100 !
#53
1/
1%
10
01
12
03
b1000 &
0(
1'
15
b101 !
#54
1(
0'
b1001 &
03
05
14
b110 !
#55
13
b1010 &
0(
1'
15
b111 !
#56
0%
02
00
0$
06
1(
0'
13
01
b1011 &
1/
05
04
0.
1-
b1000 !
#57
11
12
03
b1100 &
0(
1'
15
b1001 !
#58
1(
0'
b1101 &
03
05
14
b1010 !
#59
13
b1110 &
0(
1'
15
b1011 !
#60
0$
06
02
1/
0%
00
1(
0'
13
b1111 &
11
05
04
1.
b1100 !
#61
1$
16
0/
0%
10
01
12
03
b0 &
0(
1'
15
b1101 !
#62
1(
0'
b1 &
03
05
14
b1110 !
#63
13
b10 &
0(
1'
15
b1111 !
#64
00
0%
11
0$
06
03
02
b100 &
0/
0'
05
04
0.
0-
0,
0+
1*
b0 !
b100 "
#65
b101 &
1(
15
b1 !
#66
0(
b110 &
13
05
14
b10 !
#67
b111 &
1(
15
b11 !
#68
1/
1%
0(
03
b1000 &
01
10
05
04
1.
b100 !
#69
b1001 &
1(
15
b101 !
#70
0(
b1010 &
13
05
14
b110 !
#71
b1011 &
1(
15
b111 !
#72
0%
0$
06
0(
03
11
00
b1100 &
1/
05
04
0.
1-
b1000 !
#73
b1101 &
1(
15
b1001 !
#74
0(
b1110 &
13
05
14
b1010 !
#75
b1111 &
1(
15
b1011 !
#76
1$
16
0/
0%
0(
03
b0 &
01
10
05
04
1.
b1100 !
#77
b1 &
1(
15
b1101 !
#78
0(
b10 &
13
05
14
b1110 !
#79
b11 &
1(
15
b1111 !
#80
0$
06
03
11
00
b101 &
0/
05
04
0.
0-
1,
b0 !
b101 "
#81
13
b110 &
0(
1'
15
b1 !
#82
0/
0%
00
11
02
1(
0'
b111 &
13
05
14
b10 !
#83
1/
1%
10
01
12
03
b1000 &
0(
1'
15
b11 !
#84
02
1(
0'
03
b1001 &
01
05
04
1.
b100 !
#85
13
b1010 &
0(
1'
15
b101 !
#86
01
02
1(
0'
b1011 &
13
05
14
b110 !
#87
11
12
03
b1100 &
0(
1'
15
b111 !
#88
00
0%
02
0$
06
1(
0'
03
11
b1101 &
1/
05
04
0.
1-
b1000 !
#89
13
b1110 &
0(
1'
15
b1001 !
#90
0$
06
1/
0%
00
11
02
1(
0'
b1111 &
13
05
14
b1010 !
#91
1$
16
0/
0%
10
01
12
03
b0 &
0(
1'
15
b1011 !
#92
02
1(
0'
03
b1 &
01
05
04
1.
b1100 !
#93
13
b10 &
0(
1'
15
b1101 !
#94
01
02
1(
0'
b11 &
13
05
14
b1110 !
#95
11
12
03
b100 &
0(
1'
15
b1111 !
#96
00
02
0%
0$
06
13
11
b110 &
0/
0'
05
04
0.
0-
0,
1+
b0 !
b110 "
#97
b111 &
1(
15
b1 !
#98
1/
1%
10
01
0(
b1000 &
03
12
05
14
b10 !
#99
b1001 &
1(
15
b11 !
#100
0(
13
02
b1010 &
01
05
04
1.
b100 !
#101
b1011 &
1(
15
b101 !
#102
11
0(
b1100 &
03
12
05
14
b110 !
#103
b1101 &
1(
15
b111 !
#104
00
0%
0$
06
0(
13
02
11
b1110 &
1/
05
04
0.
1-
b1000 !
#105
b1111 &
1(
15
b1001 !
#106
1$
16
0/
0%
10
01
0(
b0 &
03
12
05
14
b1010 !
#107
b1 &
1(
15
b1011 !
#108
0(
13
02
b10 &
01
05
04
1.
b1100 !
#109
b11 &
1(
15
b1101 !
#110
11
0(
b100 &
03
12
05
14
b1110 !
#111
b101 &
1(
15
b1111 !
#112
00
0%
0$
06
13
02
11
b111 &
0/
05
04
0.
0-
1,
b0 !
b111 "
#113
1/
1%
10
01
12
03
b1000 &
0(
1'
15
b1 !
#114
1(
0'
b1001 &
03
05
14
b10 !
#115
13
b1010 &
0(
1'
15
b11 !
#116
02
1(
0'
13
b1011 &
01
05
04
1.
b100 !
#117
11
12
03
b1100 &
0(
1'
15
b101 !
#118
1(
0'
b1101 &
03
05
14
b110 !
#119
13
b1110 &
0(
1'
15
b111 !
#120
00
02
0%
0$
06
1(
0'
13
11
b1111 &
1/
05
04
0.
1-
b1000 !
#121
1$
16
0/
0%
10
01
12
03
b0 &
0(
1'
15
b1001 !
#122
1(
0'
b1 &
03
05
14
b1010 !
#123
13
b10 &
0(
1'
15
b1011 !
#124
02
1(
0'
13
b11 &
01
05
04
1.
b1100 !
#125
11
12
03
b100 &
0(
1'
15
b1101 !
#126
1(
0'
b101 &
03
05
14
b1110 !
#127
13
b110 &
0(
1'
15
b1111 !
#128
0$
06
01
1/
0%
b1000 &
03
02
00
0'
05
04
0.
0-
0,
0+
0*
1)
b0 !
b1000 "
#129
b1001 &
1(
15
b1 !
#130
0(
b1010 &
13
05
14
b10 !
#131
b1011 &
1(
15
b11 !
#132
0(
03
b1100 &
11
05
04
1.
b100 !
#133
b1101 &
1(
15
b101 !
#134
0(
b1110 &
13
05
14
b110 !
#135
b1111 &
1(
15
b111 !
#136
1%
0(
03
01
b0 &
0/
1$
16
05
04
0.
1-
b1000 !
#137
b1 &
1(
15
b1001 !
#138
0(
b10 &
13
05
14
b1010 !
#139
b11 &
1(
15
b1011 !
#140
0(
03
b100 &
11
05
04
1.
b1100 !
#141
b101 &
1(
15
b1101 !
#142
0(
b110 &
13
05
14
b1110 !
#143
b111 &
1(
15
b1111 !
#144
0%
03
01
b1001 &
1/
0$
06
05
04
0.
0-
1,
b0 !
b1001 "
#145
13
b1010 &
0(
1'
15
b1 !
#146
01
02
1(
0'
b1011 &
13
05
14
b10 !
#147
11
12
03
b1100 &
0(
1'
15
b11 !
#148
0$
06
1/
0%
02
00
1(
0'
03
b1101 &
11
05
04
1.
b100 !
#149
13
b1110 &
0(
1'
15
b101 !
#150
0$
06
1/
0%
00
11
02
1(
0'
b1111 &
13
05
14
b110 !
#151
1$
16
0/
0%
10
01
12
03
b0 &
0(
1'
15
b111 !
#152
1%
02
00
1(
0'
03
01
b1 &
0/
05
04
0.
1-
b1000 !
#153
13
b10 &
0(
1'
15
b1001 !
#154
01
02
1(
0'
b11 &
13
05
14
b1010 !
#155
11
12
03
b100 &
0(
1'
15
b1011 !
#156
0/
1%
02
00
1(
0'
03
b101 &
11
05
04
1.
b1100 !
#157
13
b110 &
0(
1'
15
b1101 !
#158
0/
1%
00
11
02
1(
0'
b111 &
13
05
14
b1110 !
#159
1/
0%
10
01
12
03
b1000 &
0(
1'
15
b1111 !
#160
0$
06
02
0%
00
13
01
b1010 &
1/
0'
05
04
0.
0-
0,
1+
b0 !
b1010 "
#161
b1011 &
1(
15
b1 !
#162
11
0(
b1100 &
03
12
05
14
b10 !
#163
b1101 &
1(
15
b11 !
#164
0$
06
1/
0%
00
0(
13
02
b1110 &
11
05
04
1.
b100 !
#165
b1111 &
1(
15
b101 !
#166
1$
16
0/
0%
10
01
0(
b0 &
03
12
05
14
b110 !
#167
b1 &
1(
15
b111 !
#168
1%
00
0(
13
02
01
b10 &
0/
05
04
0.
1-
b1000 !
#169
b11 &
1(
15
b1001 !
#170
11
0(
b100 &
03
12
05
14
b1010 !
#171
b101 &
1(
15
b1011 !
#172
0/
1%
00
0(
13
02
b110 &
11
05
04
1.
b1100 !
#173
b111 &
1(
15
b1101 !
#174
1/
0%
10
01
0(
b1000 &
03
12
05
14
b1110 !
#175
b1001 &
1(
15
b1111 !
#176
0$
06
0%
00
13
02
01
b1011 &
1/
05
04
0.
0-
1,
b0 !
b1011 "
#177
11
12
03
b1100 &
0(
1'
15
b1 !
#178
1(
0'
b1101 &
03
05
14
b10 !
#179
13
b1110 &
0(
1'
15
b11 !
#180
0$
06
02
1/
0%
00
1(
0'
13
b1111 &
11
05
04
1.
b100 !
#181
1$
16
0/
0%
10
01
12
03
b0 &
0(
1'
15
b101 !
#182
1(
0'
b1 &
03
05
14
b110 !
#183
13
b10 &
0(
1'
15
b111 !
#184
02
1%
00
1(
0'
13
01
b11 &
0/
05
04
0.
1-
b1000 !
#185
11
12
03
b100 &
0(
1'
15
b1001 !
#186
1(
0'
b101 &
03
05
14
b1010 !
#187
13
b110 &
0(
1'
15
b1011 !
#188
02
0/
1%
00
1(
0'
13
b111 &
11
05
04
1.
b1100 !
#189
1/
0%
10
01
12
03
b1000 &
0(
1'
15
b1101 !
#190
1(
0'
b1001 &
03
05
14
b1110 !
#191
13
b1010 &
0(
1'
15
b1111 !
#192
0$
06
0%
00
11
03
02
b1100 &
1/
0'
05
04
0.
0-
0,
0+
1*
b0 !
b1100 "
#193
b1101 &
1(
15
b1 !
#194
0(
b1110 &
13
05
14
b10 !
#195
b1111 &
1(
15
b11 !
#196
1$
16
0/
0%
0(
03
b0 &
01
10
05
04
1.
b100 !
#197
b1 &
1(
15
b101 !
#198
0(
b10 &
13
05
14
b110 !
#199
b11 &
1(
15
b111 !
#200
1%
0(
03
11
00
b100 &
0/
05
04
0.
1-
b1000 !
#201
b101 &
1(
15
b1001 !
#202
0(
b110 &
13
05
14
b1010 !
#203
b111 &
1(
15
b1011 !
#204
1/
0%
0(
03
b1000 &
01
10
05
04
1.
b1100 !
#205
b1001 &
1(
15
b1101 !
#206
0(
b1010 &
13
05
14
b1110 !
#207
b1011 &
1(
15
b1111 !
#208
0$
06
0%
03
11
00
b1101 &
1/
05
04
0.
0-
1,
b0 !
b1101 "
#209
13
b1110 &
0(
1'
15
b1 !
#210
0$
06
1/
0%
00
11
02
1(
0'
b1111 &
13
05
14
b10 !
#211
1$
16
0/
0%
10
01
12
03
b0 &
0(
1'
15
b11 !
#212
02
1(
0'
03
b1 &
01
05
04
1.
b100 !
#213
13
b10 &
0(
1'
15
b101 !
#214
01
02
1(
0'
b11 &
13
05
14
b110 !
#215
11
12
03
b100 &
0(
1'
15
b111 !
#216
1%
00
02
1(
0'
03
11
b101 &
0/
05
04
0.
1-
b1000 !
#217
13
b110 &
0(
1'
15
b1001 !
#218
0/
1%
00
11
02
1(
0'
b111 &
13
05
14
b1010 !
#219
1/
0%
10
01
12
03
b1000 &
0(
1'
15
b1011 !
#220
02
1(
0'
03
b1001 &
01
05
04
1.
b1100 !
#221
13
b1010 &
0(
1'
15
b1101 !
#222
01
02
1(
0'
b1011 &
13
05
14
b1110 !
#223
11
12
03
b1100 &
0(
1'
15
b1111 !
#224
0$
06
0%
00
02
13
11
b1110 &
1/
0'
05
04
0.
0-
0,
1+
b0 !
b1110 "
#225
b1111 &
1(
15
b1 !
#226
1$
16
0/
0%
10
01
0(
b0 &
03
12
05
14
b10 !
#227
b1 &
1(
15
b11 !
#228
0(
13
02
b10 &
01
05
04
1.
b100 !
#229
b11 &
1(
15
b101 !
#230
11
0(
b100 &
03
12
05
14
b110 !
#231
b101 &
1(
15
b111 !
#232
1%
00
0(
13
02
11
b110 &
0/
05
04
0.
1-
b1000 !
#233
b111 &
1(
15
b1001 !
#234
1/
0%
10
01
0(
b1000 &
03
12
05
14
b1010 !
#235
b1001 &
1(
15
b1011 !
#236
0(
13
02
b1010 &
01
05
04
1.
b1100 !
#237
b1011 &
1(
15
b1101 !
#238
11
0(
b1100 &
03
12
05
14
b1110 !
#239
b1101 &
1(
15
b1111 !
#240
0$
06
0%
00
13
02
11
b1111 &
1/
05
04
0.
0-
1,
b0 !
b1111 "
#241
1$
16
0/
0%
10
01
12
03
b0 &
0(
1'
15
b1 !
#242
1(
0'
b1 &
03
05
14
b10 !
#243
13
b10 &
0(
1'
15
b11 !
#244
02
1(
0'
13
b11 &
01
05
04
1.
b100 !
#245
11
12
03
b100 &
0(
1'
15
b101 !
#246
1(
0'
b101 &
03
05
14
b110 !
#247
13
b110 &
0(
1'
15
b111 !
#248
1%
00
02
1(
0'
13
11
b111 &
0/
05
04
0.
1-
b1000 !
#249
1/
0%
10
01
12
03
b1000 &
0(
1'
15
b1001 !
#250
1(
0'
b1001 &
03
05
14
b1010 !
#251
13
b1010 &
0(
1'
15
b1011 !
#252
02
1(
0'
13
b1011 &
01
05
04
1.
b1100 !
#253
11
12
03
b1100 &
0(
1'
15
b1101 !
#254
1(
0'
b1101 &
03
05
14
b1110 !
#255
13
b1110 &
0(
1'
15
b1111 !
#256
01
0/
03
02
00
0$
06
0'
b1 &
1(
05
04
0.
0-
0,
0+
0*
0)
1#
b0 !
b0 "
#257
13
1'
b10 &
0(
15
b1 !
#258
01
0'
02
1(
b11 &
13
05
14
b10 !
#259
11
12
03
1'
b100 &
0(
15
b11 !
#260
0/
0%
0'
02
00
1(
03
b101 &
11
05
04
1.
b100 !
#261
13
1'
b110 &
0(
15
b101 !
#262
0/
0%
00
11
0'
02
1(
b111 &
13
05
14
b110 !
#263
1/
1%
10
01
12
03
1'
b1000 &
0(
15
b111 !
#264
0%
0'
02
00
0$
06
1(
03
01
b1001 &
1/
05
04
0.
1-
b1000 !
#265
13
1'
b1010 &
0(
15
b1001 !
#266
01
0'
02
1(
b1011 &
13
05
14
b1010 !
#267
11
12
03
1'
b1100 &
0(
15
b1011 !
#268
0$
06
1/
0%
0'
02
00
1(
03
b1101 &
11
05
04
1.
b1100 !
#269
13
1'
b1110 &
0(
15
b1101 !
#270
0$
06
1/
0%
00
11
0'
02
1(
b1111 &
13
05
14
b1110 !
#271
1$
16
0/
0%
10
01
12
03
1'
b0 &
0(
15
b1111 !
#272
02
00
0$
06
13
01
b10 &
0/
05
04
0.
0-
1,
b0 !
b1 "
#273
b11 &
1(
15
b1 !
#274
11
12
0(
b100 &
03
05
14
b10 !
#275
b101 &
1(
15
b11 !
#276
0/
0%
02
00
0(
13
b110 &
11
05
04
1.
b100 !
#277
b111 &
1(
15
b101 !
#278
1/
1%
10
01
12
0(
b1000 &
03
05
14
b110 !
#279
b1001 &
1(
15
b111 !
#280
0%
02
00
0$
06
0(
13
01
b1010 &
1/
05
04
0.
1-
b1000 !
#281
b1011 &
1(
15
b1001 !
#282
11
12
0(
b1100 &
03
05
14
b1010 !
#283
b1101 &
1(
15
b1011 !
#284
0$
06
1/
0%
02
00
0(
13
b1110 &
11
05
04
1.
b1100 !
#285
b1111 &
1(
15
b1101 !
#286
1$
16
0/
0%
10
01
12
0(
b0 &
03
05
14
b1110 !
#287
b1 &
1(
15
b1111 !
#288
02
13
00
0$
06
0'
01
b11 &
0/
05
04
0.
0-
0,
1+
b0 !
b10 "
#289
11
12
03
1'
b100 &
0(
15
b1 !
#290
0'
1(
b101 &
03
05
14
b10 !
#291
13
1'
b110 &
0(
15
b11 !
#292
02
0/
0%
0'
00
1(
13
b111 &
11
05
04
1.
b100 !
#293
1/
1%
10
01
12
03
1'
b1000 &
0(
15
b101 !
#294
0'
1(
b1001 &
03
05
14
b110 !
#295
13
1'
b1010 &
0(
15
b111 !
#296
0%
02
0'
00
0$
06
1(
13
01
b1011 &
1/
05
04
0.
1-
b1000 !
#297
11
12
03
1'
b1100 &
0(
15
b1001 !
#298
0'
1(
b1101 &
03
05
14
b1010 !
#299
13
1'
b1110 &
0(
15
b1011 !
#300
02
0$
06
1/
0%
0'
00
1(
13
b1111 &
11
05
04
1.
b1100 !
#301
1$
16
0/
0%
10
01
12
03
1'
b0 &
0(
15
b1101 !
#302
0'
1(
b1 &
03
05
14
b1110 !
#303
13
1'
b10 &
0(
15
b1111 !
#304
00
0$
06
03
11
b100 &
0/
05
04
0.
0-
1,
b0 !
b11 "
#305
b101 &
1(
15
b1 !
#306
0(
b110 &
13
05
14
b10 !
#307
b111 &
1(
15
b11 !
#308
1/
1%
10
0(
03
b1000 &
01
05
04
1.
b100 !
#309
b1001 &
1(
15
b101 !
#310
0(
b1010 &
13
05
14
b110 !
#311
b1011 &
1(
15
b111 !
#312
0%
00
0$
06
0(
03
11
b1100 &
1/
05
04
0.
1-
b1000 !
#313
b1101 &
1(
15
b1001 !
#314
0(
b1110 &
13
05
14
b1010 !
#315
b1111 &
1(
15
b1011 !
#316
1$
16
0/
0%
10
0(
03
b0 &
01
05
04
1.
b1100 !
#317
b1 &
1(
15
b1101 !
#318
0(
b10 &
13
05
14
b1110 !
#319
b11 &
1(
15
b1111 !
#320
00
0%
03
11
0$
06
0'
02
b101 &
0/
05
04
0.
0-
0,
0+
1*
b0 !
b100 "
#321
13
1'
b110 &
0(
15
b1 !
#322
0/
0%
00
11
0'
02
1(
b111 &
13
05
14
b10 !
#323
1/
1%
10
01
12
03
1'
b1000 &
0(
15
b11 !
#324
0'
02
1(
03
b1001 &
01
05
04
1.
b100 !
#325
13
1'
b1010 &
0(
15
b101 !
#326
01
0'
02
1(
b1011 &
13
05
14
b110 !
#327
11
12
03
1'
b1100 &
0(
15
b111 !
#328
00
0%
0'
02
0$
06
1(
03
11
b1101 &
1/
05
04
0.
1-
b1000 !
#329
13
1'
b1110 &
0(
15
b1001 !
#330
0$
06
1/
0%
00
11
0'
02
1(
b1111 &
13
05
14
b1010 !
#331
1$
16
0/
0%
10
01
12
03
1'
b0 &
0(
15
b1011 !
#332
0'
02
1(
03
b1 &
01
05
04
1.
b1100 !
#333
13
1'
b10 &
0(
15
b1101 !
#334
01
0'
02
1(
b11 &
13
05
14
b1110 !
#335
11
12
03
1'
b100 &
0(
15
b1111 !
#336
00
0%
02
0$
06
13
11
b110 &
0/
05
04
0.
0-
1,
b0 !
b101 "
#337
b111 &
1(
15
b1 !
#338
1/
1%
10
01
12
0(
b1000 &
03
05
14
b10 !
#339
b1001 &
1(
15
b11 !
#340
02
0(
13
b1010 &
01
05
04
1.
b100 !
#341
b1011 &
1(
15
b101 !
#342
11
12
0(
b1100 &
03
05
14
b110 !
#343
b1101 &
1(
15
b111 !
#344
00
0%
02
0$
06
0(
13
11
b1110 &
1/
05
04
0.
1-
b1000 !
#345
b1111 &
1(
15
b1001 !
#346
1$
16
0/
0%
10
01
12
0(
b0 &
03
05
14
b1010 !
#347
b1 &
1(
15
b1011 !
#348
02
0(
13
b10 &
01
05
04
1.
b1100 !
#349
b11 &
1(
15
b1101 !
#350
11
12
0(
b100 &
03
05
14
b1110 !
#351
b101 &
1(
15
b1111 !
#352
00
02
0%
13
0$
06
0'
11
b111 &
0/
05
04
0.
0-
0,
1+
b0 !
b110 "
#353
1/
1%
10
01
12
03
1'
b1000 &
0(
15
b1 !
#354
0'
1(
b1001 &
03
05
14
b10 !
#355
13
1'
b1010 &
0(
15
b11 !
#356
02
0'
1(
13
b1011 &
01
05
04
1.
b100 !
#357
11
12
03
1'
b1100 &
0(
15
b101 !
#358
0'
1(
b1101 &
03
05
14
b110 !
#359
13
1'
b1110 &
0(
15
b111 !
#360
00
02
0%
0'
0$
06
1(
13
11
b1111 &
1/
05
04
0.
1-
b1000 !
#361
1$
16
0/
0%
10
01
12
03
1'
b0 &
0(
15
b1001 !
#362
0'
1(
b1 &
03
05
14
b1010 !
#363
13
1'
b10 &
0(
15
b1011 !
#364
02
0'
1(
13
b11 &
01
05
04
1.
b1100 !
#365
11
12
03
1'
b100 &
0(
15
b1101 !
#366
0'
1(
b101 &
03
05
14
b1110 !
#367
13
1'
b110 &
0(
15
b1111 !
#368
1%
0$
06
03
01
b1000 &
1/
05
04
0.
0-
1,
b0 !
b111 "
#369
b1001 &
1(
15
b1 !
#370
0(
b1010 &
13
05
14
b10 !
#371
b1011 &
1(
15
b11 !
#372
0(
03
b1100 &
11
05
04
1.
b100 !
#373
b1101 &
1(
15
b101 !
#374
0(
b1110 &
13
05
14
b110 !
#375
b1111 &
1(
15
b111 !
#376
0%
1$
16
0(
03
01
b0 &
0/
05
04
0.
1-
b1000 !
#377
b1 &
1(
15
b1001 !
#378
0(
b10 &
13
05
14
b1010 !
#379
b11 &
1(
15
b1011 !
#380
0(
03
b100 &
11
05
04
1.
b1100 !
#381
b101 &
1(
15
b1101 !
#382
0(
b110 &
13
05
14
b1110 !
#383
b111 &
1(
15
b1111 !
#384
0$
06
03
01
b1001 &
1/
0%
0'
02
00
05
04
0.
0-
0,
0+
0*
1)
b0 !
b1000 "
#385
13
1'
b1010 &
0(
15
b1 !
#386
01
0'
02
1(
b1011 &
13
05
14
b10 !
#387
11
12
03
1'
b1100 &
0(
15
b11 !
#388
0$
06
1/
0%
0'
02
00
1(
03
b1101 &
11
05
04
1.
b100 !
#389
13
1'
b1110 &
0(
15
b101 !
#390
0$
06
1/
0%
00
11
0'
02
1(
b1111 &
13
05
14
b110 !
#391
1$
16
0/
0%
10
01
12
03
1'
b0 &
0(
15
b111 !
#392
1%
0'
02
00
1(
03
01
b1 &
0/
05
04
0.
1-
b1000 !
#393
13
1'
b10 &
0(
15
b1001 !
#394
01
0'
02
1(
b11 &
13
05
14
b1010 !
#395
11
12
03
1'
b100 &
0(
15
b1011 !
#396
0/
1%
0'
02
00
1(
03
b101 &
11
05
04
1.
b1100 !
#397
13
1'
b110 &
0(
15
b1101 !
#398
0/
1%
00
11
0'
02
1(
b111 &
13
05
14
b1110 !
#399
1/
0%
10
01
12
03
1'
b1000 &
0(
15
b1111 !
#400
0$
06
0%
02
00
13
01
b1010 &
1/
05
04
0.
0-
1,
b0 !
b1001 "
#401
b1011 &
1(
15
b1 !
#402
11
12
0(
b1100 &
03
05
14
b10 !
#403
b1101 &
1(
15
b11 !
#404
0$
06
1/
0%
02
00
0(
13
b1110 &
11
05
04
1.
b100 !
#405
b1111 &
1(
15
b101 !
#406
1$
16
0/
0%
10
01
12
0(
b0 &
03
05
14
b110 !
#407
b1 &
1(
15
b111 !
#408
1%
02
00
0(
13
01
b10 &
0/
05
04
0.
1-
b1000 !
#409
b11 &
1(
15
b1001 !
#410
11
12
0(
b100 &
03
05
14
b1010 !
#411
b101 &
1(
15
b1011 !
#412
0/
1%
02
00
0(
13
b110 &
11
05
04
1.
b1100 !
#413
b111 &
1(
15
b1101 !
#414
1/
0%
10
01
12
0(
b1000 &
03
05
14
b1110 !
#415
b1001 &
1(
15
b1111 !
#416
0$
06
02
0%
13
00
0'
01
b1011 &
1/
05
04
0.
0-
0,
1+
b0 !
b1010 "
#417
11
12
03
1'
b1100 &
0(
15
b1 !
#418
0'
1(
b1101 &
03
05
14
b10 !
