Lab 2/alu.v
/*
 * Generated by Digital. Don't modify this file!
 * Any changes will be lost if this file is regenerated.
 */

module half_adder (
  input a,
  input b,
  output sum,
  output cry
);
  assign sum = (a ^ b);
  assign cry = (a & b);
endmodule

module incrementer (
  input inc,
  input [3:0] a,
  output [3:0] y,
  output cry
);
  wire s0;
  wire s1;
  wire s2;
  wire s3;
  wire s4;
  wire s5;
  wire s6;
  wire s7;
  wire s8;
  wire s9;
  wire s10;
  assign s4 = a[3];
  assign s5 = a[2];
  assign s1 = a[1];
  assign s6 = a[0];
  half_adder half_adder_i0 (
    .a( s6 ),
    .b( inc ),
    .sum( s10 ),
    .cry( s0 )
  );
  half_adder half_adder_i1 (
    .a( s0 ),
    .b( s1 ),
    .sum( s2 ),
    .cry( s3 )
  );
  half_adder half_adder_i2 (
    .a( s3 ),
    .b( s5 ),
    .sum( s7 ),
    .cry( s8 )
  );
  half_adder half_adder_i3 (
    .a( s8 ),
    .b( s4 ),
    .sum( s9 ),
    .cry( cry )
  );
  assign y[3] = s9;
  assign y[2] = s7;
  assign y[1] = s2;
  assign y[0] = s10;
endmodule

module not_neg (
  input [3:0] a,
  input invert,
  input neg,
  output [3:0] y,
  output cry
);
  wire s0;
  wire [3:0] s1;
  assign s0 = (invert & neg);
  assign s1[0] = (a[0] ^ invert);
  assign s1[1] = (a[1] ^ invert);
  assign s1[2] = (a[2] ^ invert);
  assign s1[3] = (a[3] ^ invert);
  incrementer incrementer_i0 (
    .inc( s0 ),
    .a( s1 ),
    .y( y ),
    .cry( cry )
  );
endmodule

module full_adder (
  input a,
  input b,
  input cin,
  output sum,
  output cout
);
  assign sum = (a ^ b ^ cin);
  assign cout = ((b & cin) | (cin & a) | (b & a));
endmodule

module four_bit_adder (
  input [3:0] a,
  input [3:0] b,
  input cin,
  output [3:0] y,
  output overfl,
  output cout
);
  wire s0;
  wire s1;
  wire s2;
  wire s3;
  wire s4;
  wire s5;
  wire s6;
  wire s7;
  wire s8;
  wire s9;
  wire s10;
  wire s11;
  wire s12;
  wire s13;
  wire s14;
  wire cout_temp;
  assign s0 = a[0];
  assign s1 = a[1];
  assign s2 = a[2];
  assign s3 = a[3];
  assign s4 = b[0];
  assign s5 = b[1];
  assign s6 = b[2];
  assign s7 = b[3];
  full_adder full_adder_i0 (
    .a( s0 ),
    .b( s4 ),
    .cin( cin ),
    .sum( s8 ),
    .cout( s9 )
  );
  full_adder full_adder_i1 (
    .a( s1 ),
    .b( s5 ),
    .cin( s9 ),
    .sum( s10 ),
    .cout( s11 )
  );
  full_adder full_adder_i2 (
    .a( s2 ),
    .b( s6 ),
    .cin( s11 ),
    .sum( s12 ),
    .cout( s13 )
  );
  full_adder full_adder_i3 (
    .a( s3 ),
    .b( s7 ),
    .cin( s13 ),
    .sum( s14 ),
    .cout( cout_temp )
  );
  assign y[0] = s8;
  assign y[1] = s10;
  assign y[2] = s12;
  assign y[3] = s14;
  assign overfl = (s13 ^ cout_temp);
  assign cout = cout_temp;
endmodule

module two_bit_mux (
  input a,
  input b,
  input s,
  output y
);
  assign y = ((a & ~ s) | (s & b));
endmodule

module four_bit_mux (
  input [3:0] a,
  input [3:0] b,
  input sel,
  output [3:0] y
);
  wire s0;
  wire s1;
  wire s2;
  wire s3;
  wire s4;
  wire s5;
  wire s6;
  wire s7;
  wire s8;
  wire s9;
  wire s10;
  wire s11;
  assign s0 = a[0];
  assign s1 = a[1];
  assign s2 = a[2];
  assign s3 = a[3];
  assign s4 = b[0];
  assign s5 = b[1];
  assign s6 = b[2];
  assign s7 = b[3];
  two_bit_mux two_bit_mux_i0 (
    .a( s0 ),
    .b( s4 ),
    .s( sel ),
    .y( s8 )
  );
  two_bit_mux two_bit_mux_i1 (
    .a( s1 ),
    .b( s5 ),
    .s( sel ),
    .y( s9 )
  );
  two_bit_mux two_bit_mux_i2 (
    .a( s2 ),
    .b( s6 ),
    .s( sel ),
    .y( s10 )
  );
  two_bit_mux two_bit_mux_i3 (
    .a( s3 ),
    .b( s7 ),
    .s( sel ),
    .y( s11 )
  );
  assign y[0] = s8;
  assign y[1] = s9;
  assign y[2] = s10;
  assign y[3] = s11;
endmodule

module and_add (
  input [3:0] a,
  input [3:0] b,
  input cin,
  input add,
  input pass,
  output cout,
  output overfl,
  output [3:0] y
);
  wire [3:0] s0;
  wire [3:0] s1;
  wire [3:0] s2;
  four_bit_adder four_bit_adder_i0 (
    .a( a ),
    .b( b ),
    .cin( cin ),
    .y( s0 ),
    .overfl( overfl ),
    .cout( cout )
  );
  assign s1[0] = (a[0] & b[0]);
  assign s1[1] = (a[1] & b[1]);
  assign s1[2] = (a[2] & b[2]);
  assign s1[3] = (a[3] & b[3]);
  four_bit_mux four_bit_mux_i1 (
    .a( s1 ),
    .b( s0 ),
    .sel( add ),
    .y( s2 )
  );
  four_bit_mux four_bit_mux_i2 (
    .a( s2 ),
    .b( a ),
    .sel( pass ),
    .y( y )
  );
endmodule

module alu (
  input [3:0] a,
  input invert,
  input [3:0] b,
  input arith,
  input cin,
  input pass,
  output cout,
  output overfl,
  output [3:0] y
);
  wire [3:0] s0;
  not_neg not_neg_i0 (
    .a( a ),
    .invert( invert ),
    .neg( arith ),
    .y( s0 )
  );
  and_add and_add_i1 (
    .a( s0 ),
    .b( b ),
    .cin( cin ),
    .add( arith ),
    .pass( pass ),
    .cout( cout ),
    .overfl( overfl ),
    .y( y )
  );
endmodule

Lab 2/four_bit_mux_top.v
// Test module for lab 0
`timescale 1ns/1ns          // set a realistic time scale for the simulation

module four_bit_mux_top();

reg [15:0] resp_data[0:7];  // stimulus and response. This array is 8 rows and 16 columns
reg [3:0] in_a;             // the A input to the circuit
reg [3:0] in_b;             // the B input to the circuit
reg in_s;                   // the S input to the circuit
wire [3:0] out_y;           // the Y output
reg [3:0] exp_out;          // the expected output

integer index;              // index into the input/output arrays

initial                     // read the arrays
begin
   $readmemh("four_bit_mux_stim.txt",resp_data);  // read the inputs and expected respnses
end

initial    // all initial blocks run at start up...
begin
   for ( index = 0 ; index < 8 ; index = index+1 )  // for each of the rows in the table
   begin
      //$display(resp_data[index]);
      {in_s,in_a,in_b} = resp_data[index][8:0];     // get the next inputs.

      exp_out = resp_data[index][15:12];            // get the expected outputs.

      #10;                                // wait for propagation
      if ( out_y != exp_out )             // did we get what was expected?
         $display("Output mismatch for entry ",index," expected ",
                  exp_out," but got out_y ",out_y);
   end
end

// this instantiates your design
four_bit_mux four_bit_mux(.a(in_a),.b(in_b),.sel(in_s), .y(out_y)); 

// dump the output to a VCD file so the waveform viewer can create the display
initial
begin
   $dumpfile("four_bit_mux_waves.vcd"); // the name of the output file containing the waves
   $dumpvars(0,four_bit_mux);           // 0 dumps all signals from full_adder down
end

endmodule

Lab 2/four_bit_mux_waves.vcd
$date
	Thu Feb 19 14:30:57 2026
$end
$version
	Icarus Verilog
$end
$timescale
	1ns
$end
$scope module four_bit_mux_top $end
$scope module four_bit_mux $end
$var wire 4 ! a [3:0] $end
$var wire 4 " b [3:0] $end
$var wire 1 # sel $end
$var wire 4 $ y [3:0] $end
$var wire 1 % s9 $end
$var wire 1 & s8 $end
$var wire 1 ' s7 $end
$var wire 1 ( s6 $end
$var wire 1 ) s5 $end
$var wire 1 * s4 $end
$var wire 1 + s3 $end
$var wire 1 , s2 $end
$var wire 1 - s11 $end
$var wire 1 . s10 $end
$var wire 1 / s1 $end
$var wire 1 0 s0 $end
$scope module two_bit_mux_i0 $end
$var wire 1 0 a $end
$var wire 1 * b $end
$var wire 1 # s $end
$var wire 1 & y $end
$upscope $end
$scope module two_bit_mux_i1 $end
$var wire 1 / a $end
$var wire 1 ) b $end
$var wire 1 # s $end
$var wire 1 % y $end
$upscope $end
$scope module two_bit_mux_i2 $end
$var wire 1 , a $end
$var wire 1 ( b $end
$var wire 1 # s $end
$var wire 1 . y $end
$upscope $end
$scope module two_bit_mux_i3 $end
$var wire 1 + a $end
$var wire 1 ' b $end
$var wire 1 # s $end
$var wire 1 - y $end
$upscope $end
$upscope $end
$upscope $end
$enddefinitions $end
$comment Show the parameter values. $end
$dumpall
$end
#0
$dumpvars
10
0/
0.
0-
0,
0+
0*
0)
0(
0'
1&
0%
b1 $
0#
b0 "
b1 !
$end
#10
00
1*
1#
b0 !
b1 "
#20
b0 $
0&
0*
b0 "
#30
1&
1%
1.
b1111 $
1-
1*
1)
1(
1'
b1111 "
#40
10
1/
1,
1+
0*
0)
0(
0'
0#
b1111 !
b0 "
#50
1*
1(
1'
b1101 "
#60
0/
1)
1#
b1101 !
b1111 "
#70
0&
0%
b1000 $
0.
00
0,
0+
0*
0)
0(
b0 !
b1000 "
